{"title":"139","lines":[{"lineNumber":1,"line":"O! call not me to justify the wrong"},{"lineNumber":2,"line":"That thy unkindness lays upon my heart;"},{"lineNumber":3,"line":"Wound me not with thine eye, but with thy tongue:"},{"lineNumber":4,"line":"Use power with power, and slay me not by art,"},{"lineNumber":5,"line":"Tell me thou lov'st elsewhere; but in my sight,"},{"lineNumber":6,"line":"Dear heart, forbear to glance thine eye aside:"},{"lineNumber":7,"line":"What need'st thou wound with cunning, when thy might"},{"lineNumber":8,"line":"Is more than my o'erpress'd defence can bide?"},{"lineNumber":9,"line":"Let me excuse thee: ah! my love well knows"},{"lineNumber":10,"line":"Her pretty looks have been mine enemies;"},{"lineNumber":11,"line":"And therefore from my face she turns my foes,"},{"lineNumber":12,"line":"That they elsewhere might dart their injuries:"},{"lineNumber":13,"line":"Yet do not so; but since I am near slain, "},{"lineNumber":14,"line":"Kill me outright with looks, and rid my pain."}]}