{"title":"145","lines":[{"lineNumber":1,"line":"Those lips that Love's own hand did make,"},{"lineNumber":2,"line":"Breathed forth the sound that said 'I hate',"},{"lineNumber":3,"line":"To me that languish'd for her sake:"},{"lineNumber":4,"line":"But when she saw my woeful state,"},{"lineNumber":5,"line":"Straight in her heart did mercy come,"},{"lineNumber":6,"line":"Chiding that tongue that ever sweet"},{"lineNumber":7,"line":"Was us'd in giving gentle doom;"},{"lineNumber":8,"line":"And taught it thus anew to greet;"},{"lineNumber":9,"line":"'I hate' she alter'd with an end,"},{"lineNumber":10,"line":"That followed it as gentle day,"},{"lineNumber":11,"line":"Doth follow night, who like a fiend"},{"lineNumber":12,"line":"From heaven to hell is flown away."},{"lineNumber":13,"line":"'I hate', from hate away she threw,"},{"lineNumber":14,"line":"And sav'd my life, saying 'not you'."}]}