{"title":"86","lines":[{"lineNumber":1,"line":"Was it the proud full sail of his great verse,"},{"lineNumber":2,"line":"Bound for the prize of all too precious you,"},{"lineNumber":3,"line":"That did my ripe thoughts in my brain inhearse,"},{"lineNumber":4,"line":"Making their tomb the womb wherein they grew?"},{"lineNumber":5,"line":"Was it his spirit, by spirits taught to write,"},{"lineNumber":6,"line":"Above a mortal pitch, that struck me dead?"},{"lineNumber":7,"line":"No, neither he, nor his compeers by night"},{"lineNumber":8,"line":"Giving him aid, my verse astonished."},{"lineNumber":9,"line":"He, nor that affable familiar ghost"},{"lineNumber":10,"line":"Which nightly gulls him with intelligence,"},{"lineNumber":11,"line":"As victors of my silence cannot boast;"},{"lineNumber":12,"line":"I was not sick of any fear from thence:"},{"lineNumber":13,"line":"But when your countenance fill'd up his line,"},{"lineNumber":14,"line":"Then lacked I matter; that enfeebled mine."}]}